taggr/__init__.py
taggr/cli.py
taggr/sql.py
taggr-0.2.0.dist-info/LICENSE.AGPLv3
taggr-0.2.0.dist-info/METADATA
taggr-0.2.0.dist-info/WHEEL
taggr-0.2.0.dist-info/entry_points.txt
taggr-0.2.0.dist-info/top_level.txt
taggr-0.2.0.dist-info/RECORD
